stdio_mgr/__init__.py
stdio_mgr/__version__.py
stdio_mgr/stdio_mgr.py
stdio_mgr-1.0.1.dist-info/LICENSE.txt
stdio_mgr-1.0.1.dist-info/METADATA
stdio_mgr-1.0.1.dist-info/WHEEL
stdio_mgr-1.0.1.dist-info/top_level.txt
stdio_mgr-1.0.1.dist-info/RECORD
