Metadata-Version: 1.2
Name: stdio-mgr
Version: 1.0.1
Summary: Context manager for mocking/wrapping stdin/stdout/stderr
Home-page: https://www.github.com/bskinn/stdio-mgr
Author: Brian Skinn
Author-email: bskinn@alum.mit.edu
License: MIT License
Platform: UNKNOWN
Classifier: License :: OSI Approved :: MIT License
Classifier: Natural Language :: English
Classifier: Intended Audience :: Developers
Classifier: Operating System :: OS Independent
Classifier: Programming Language :: Python :: 3
Classifier: Programming Language :: Python :: 3 :: Only
Classifier: Programming Language :: Python :: 3.3
Classifier: Programming Language :: Python :: 3.4
Classifier: Programming Language :: Python :: 3.5
Classifier: Programming Language :: Python :: 3.6
Classifier: Programming Language :: Python :: 3.7
Classifier: Topic :: Software Development :: Libraries :: Python Modules
Classifier: Topic :: Software Development :: Testing
Classifier: Development Status :: 5 - Production/Stable
Requires: attrs (>=17.1)
Provides: stdio_mgr
Requires-Python: >=3
